Metadata-Version: 2.1
Name: pro-video-ferramentas-gutierri
Version: 1.0
Summary: Este pacote irá fornecer ferramentas de processamento de video 
Author: Allef gutierri
Author-email: allef@yahoo.com
Keywords: camera,processamento,video
License-File: license.txt
